secret/SCRATCH.py
secret/__init__.py
suggestion/__init__.py
suggestion/__main__.py
suggestion/constant/__init__.py
suggestion/demo/__init__.py
suggestion/demo/__main__.py
suggestion/dropdown/__init__.py
suggestion/dto/__init__.py
suggestion/engine/__init__.py
suggestion/error/__init__.py
suggestion/hooking/__init__.py
suggestion/hooking/ante_build_hook.py
suggestion/hooking/ante_release_hook.py
suggestion/hooking/post_build_hook.py
suggestion/hooking/post_release_hook.py
suggestion/pyrustic_data/hooking.json
suggestion/pyrustic_data/hubstore.json
suggestion/pyrustic_data/release_info.json
suggestion/pyrustic_data/backstage/config/build.json
suggestion/pyrustic_data/backstage/config/init.json
suggestion/pyrustic_data/backstage/config/release.json
suggestion/pyrustic_data/backstage/data/build_report.json
suggestion/pyrustic_data/backstage/data/github_release_form.json
suggestion/pyrustic_data/backstage/hooking/build.json
suggestion/pyrustic_data/backstage/hooking/init.json
suggestion/pyrustic_data/backstage/hooking/release.json
suggestion/pyrustic_data/backstage/report/build_report.json
suggestion/pyrustic_data/backstage/report/release_report.json
suggestion/pyrustic_data/hubstore/img.json
suggestion/pyrustic_data/hubstore/promotion.json
tests/__init__.py
tests/__main__.py
suggestion-0.0.7.dist-info/LICENSE
suggestion-0.0.7.dist-info/METADATA
suggestion-0.0.7.dist-info/WHEEL
suggestion-0.0.7.dist-info/entry_points.txt
suggestion-0.0.7.dist-info/top_level.txt
suggestion-0.0.7.dist-info/RECORD
