Metadata-Version: 2.1
Name: suggestion
Version: 0.0.7
Summary: Democratizing auto-complete(suggest) for Python desktop applications
Home-page: https://github.com/pyrustic/suggestion
Author: Pyrustic Evangelist
Author-email: rusticalex@yahoo.com
Maintainer: Pyrustic Evangelist
Maintainer-email: rusticalex@yahoo.com
License: MIT
Keywords: auto-complete,auto-suggest,gui,desktop-app,autocomplete,frontend,tkinter,app,lightweight,pyrustic
Platform: UNKNOWN
Classifier: Programming Language :: Python :: 3
Classifier: License :: OSI Approved :: MIT License
Classifier: Operating System :: OS Independent
Requires-Python: >=3.5
License-File: LICENSE
Requires-Dist: viewable
